data_grid/__init__.py
data_grid/register.py
data_grid/frontend/dist/index.html
data_grid/frontend/dist/vite.svg
data_grid/frontend/dist/assets/html2canvas.esm-7570f311-59a6f546.js
data_grid/frontend/dist/assets/index-d081bea5.css
data_grid/frontend/dist/assets/index-dffa65a7.js
data_grid/frontend/dist/assets/index.es-650b637d-a0b9f247.js
data_grid/frontend/dist/assets/purify.es-958e7803-b3d8833e.js
test_data_grid-0.0.1.dist-info/LICENSE
test_data_grid-0.0.1.dist-info/METADATA
test_data_grid-0.0.1.dist-info/WHEEL
test_data_grid-0.0.1.dist-info/top_level.txt
test_data_grid-0.0.1.dist-info/RECORD
