Metadata-Version: 2.1
Name: test-data-grid
Version: 0.0.1
Summary: Show data in data grid
Home-page: UNKNOWN
Author: Bluepinapple
Author-email: viveksthul@bluepinapple.com
License: UNKNOWN
Platform: UNKNOWN
Requires-Python: >=3.9.6
Requires-Dist: streamlit (>=1.20.0)
